{"OutputFileHashSum":"735DEA8F96284E344B02F2D37A4D3049B9219050164332F64DFFB7D6238BD13B","Converted":true,"OutputModifyDate":"2025-10-16T08:43:41.338707Z","Metadatas":[],"MetadataTypes":[{"CategoryName":"VuGen.Replay","MetadataTypeName":"Utt.Debugger.Warning","Id":1},{"CategoryName":"VuGen.Replay","MetadataTypeName":"HP.LR.Vugen.NotifyTransaction","Id":2},{"CategoryName":"VuGen.Replay","MetadataTypeName":"Utt.Debugger.Error","Id":3},{"CategoryName":"VuGen.Replay","MetadataTypeName":"HP.LR.Vugen.NotifyAny","Id":4}]}